Metadata-Version: 2.1
Name: invoicing-xl-pdf
Version: 1.0.0
Summary: You can use this package to turn Excel files into PDF files.
Home-page: https://github.com/lorenzoheine
Author: Lorenzo Heine
Author-email: personaldevmail@egmail.com
License: MIT
Keywords: invoice,excel,pdf
Classifier: Development Status :: 3 - Alpha
Classifier: Intended Audience :: Developers
Classifier: Topic :: Software Development :: Build Tools
Classifier: License :: OSI Approved :: MIT License
Classifier: Programming Language :: Python :: 3.8
Classifier: Programming Language :: Python :: 3.9
Classifier: Programming Language :: Python :: 3.10
Classifier: Programming Language :: Python :: 3.11
